<?xml version="1.0" encoding="utf-8"?>
<scene PGFVersion="0.19" GSCVersion="0.10.4" id="id379280">
  <layers>
    <layer id="id487678">
      <actors>
        <actor id="id709522" prototype="id732816">
          <attributes>
            <point id="position">
              <real id="x">127.5</real>
              <real id="y">25</real>
            </point>
            <size id="size">
              <real id="width">52</real>
              <real id="height">44</real>
            </size>
            <angle id="rotation">0</angle>
          </attributes>
          <behaviors>
            <behavior id="id305491" class="MoveBehavior" enabled="true">
              <attributes>
                <text id="name">Move</text>
                <text id="bundleName">Move.behavior</text>
                <angle id="direction">180</angle>
                <index id="space">0</index>
                <index id="moveType">0</index>
                <real id="speed">25</real>
              </attributes>
            </behavior>
          </behaviors>
          <aspects>
            <graphics>
              <attributes>
                <integer id="tileWidth" name="tileWidth">0</integer>
                <integer id="tileHeight" name="tileHeight">0</integer>
              </attributes>
            </graphics>
            <motion />
            <physics>
              <attributes />
            </physics>
          </aspects>
        </actor>
        <actor id="id501236" prototype="id681254">
          <attributes>
            <point id="position">
              <real id="x">277</real>
              <real id="y">271.5</real>
            </point>
            <size id="size">
              <real id="width">52</real>
              <real id="height">96</real>
            </size>
            <angle id="rotation">0</angle>
          </attributes>
          <behaviors>
            <behavior id="id449344" class="MoveBehavior" enabled="true">
              <attributes>
                <text id="name">Move</text>
                <text id="bundleName">Move.behavior</text>
                <angle id="direction">180</angle>
                <index id="space">0</index>
                <index id="moveType">0</index>
                <real id="speed">25</real>
              </attributes>
            </behavior>
          </behaviors>
          <aspects>
            <graphics>
              <attributes>
                <integer id="tileWidth" name="tileWidth">0</integer>
                <integer id="tileHeight" name="tileHeight">0</integer>
              </attributes>
            </graphics>
            <motion />
            <physics>
              <attributes />
            </physics>
          </aspects>
        </actor>
        <actor id="id106284" prototype="id820425">
          <attributes>
            <point id="position">
              <real id="x">276</real>
              <real id="y">59.5</real>
            </point>
            <size id="size">
              <real id="width">57</real>
              <real id="height">115</real>
            </size>
            <angle id="rotation">0</angle>
          </attributes>
          <behaviors>
            <behavior id="id233289" class="MoveBehavior" enabled="true">
              <attributes>
                <text id="name">Move</text>
                <text id="bundleName">Move.behavior</text>
                <angle id="direction">180</angle>
                <index id="space">0</index>
                <index id="moveType">0</index>
                <real id="speed">25</real>
              </attributes>
            </behavior>
          </behaviors>
          <aspects>
            <graphics>
              <attributes>
                <integer id="tileWidth" name="tileWidth">0</integer>
                <integer id="tileHeight" name="tileHeight">0</integer>
              </attributes>
            </graphics>
            <motion />
            <physics>
              <attributes />
            </physics>
          </aspects>
        </actor>
        <actor id="id833358" prototype="id134261">
          <attributes>
            <point id="position">
              <real id="x">27.5</real>
              <real id="y">83</real>
            </point>
            <size id="size">
              <real id="width">55</real>
              <real id="height">44</real>
            </size>
            <angle id="rotation">0</angle>
          </attributes>
          <behaviors>
            <behavior id="id919195" class="RuleBehavior" enabled="true">
              <attributes>
                <text id="name">Rule</text>
                <text id="bundleName">Rule.behavior</text>
                <real id="compoundConditionKind">0</real>
              </attributes>
              <conditions>
                <condition id="id832968" eventType="key" pluginPredicateTypeIndex="0" class="Key">
                  <attributes>
                    <text id="name">default name</text>
                    <index id="conditionType">0</index>
                  </attributes>
                  <predicate type="key">
                    <attributes>
                      <text id="mode">down</text>
                      <text id="keyString">up</text>
                    </attributes>
                  </predicate>
                </condition>
              </conditions>
              <behaviors>
                <behavior id="id524429" class="MoveBehavior" enabled="true">
                  <attributes>
                    <text id="name">Move</text>
                    <text id="bundleName">Move.behavior</text>
                    <angle id="direction">90</angle>
                    <index id="space">0</index>
                    <index id="moveType">0</index>
                    <real id="speed">150</real>
                  </attributes>
                </behavior>
              </behaviors>
            </behavior>
            <behavior id="id704112" class="TimerBehavior" enabled="true">
              <attributes>
                <text id="name">Timer</text>
                <text id="bundleName">Timer.behavior</text>
                <index id="timerType">0</index>
                <real id="interval">0.5</real>
                <boolean id="runToCompletion">false</boolean>
              </attributes>
              <behaviors>
                <behavior id="id533290" class="MoveToBehavior" enabled="true">
                  <attributes>
                    <text id="name">Move To</text>
                    <text id="bundleName">MoveTo.behavior</text>
                    <boolean id="runToCompletion">false</boolean>
                    <point id="position">
                      <real id="x">
                        <expression>
                          <reference keypath="self.attributes.position.x" />
                        </expression>
                      </real>
                      <real id="y">0</real>
                    </point>
                    <index id="space">1</index>
                    <real id="speed">800</real>
                  </attributes>
                </behavior>
              </behaviors>
            </behavior>
          </behaviors>
          <aspects>
            <graphics>
              <attributes>
                <integer id="tileWidth" name="tileWidth">0</integer>
                <integer id="tileHeight" name="tileHeight">0</integer>
              </attributes>
            </graphics>
            <motion />
            <physics>
              <attributes />
            </physics>
          </aspects>
        </actor>
        <actor id="id966899" prototype="id125488">
          <attributes>
            <point id="position">
              <real id="x">411</real>
              <real id="y">34</real>
            </point>
            <size id="size">
              <real id="width">61</real>
              <real id="height">63</real>
            </size>
            <angle id="rotation">0</angle>
          </attributes>
          <behaviors>
            <behavior id="id263411" class="MoveBehavior" enabled="true">
              <attributes>
                <text id="name">Move</text>
                <text id="bundleName">Move.behavior</text>
                <angle id="direction">180</angle>
                <index id="space">0</index>
                <index id="moveType">0</index>
                <real id="speed">25</real>
              </attributes>
            </behavior>
          </behaviors>
          <aspects>
            <graphics>
              <attributes>
                <integer id="tileWidth" name="tileWidth">0</integer>
                <integer id="tileHeight" name="tileHeight">0</integer>
              </attributes>
            </graphics>
            <motion />
            <physics>
              <attributes />
            </physics>
          </aspects>
        </actor>
        <actor id="id592858" prototype="id751623">
          <attributes>
            <point id="position">
              <real id="x">409</real>
              <real id="y">239.5</real>
            </point>
            <size id="size">
              <real id="width">63</real>
              <real id="height">157</real>
            </size>
            <angle id="rotation">0</angle>
          </attributes>
          <behaviors>
            <behavior id="id340995" class="MoveBehavior" enabled="true">
              <attributes>
                <text id="name">Move</text>
                <text id="bundleName">Move.behavior</text>
                <angle id="direction">180</angle>
                <index id="space">0</index>
                <index id="moveType">0</index>
                <real id="speed">25</real>
              </attributes>
            </behavior>
          </behaviors>
          <aspects>
            <graphics>
              <attributes>
                <integer id="tileWidth" name="tileWidth">0</integer>
                <integer id="tileHeight" name="tileHeight">0</integer>
              </attributes>
            </graphics>
            <motion />
            <physics>
              <attributes />
            </physics>
          </aspects>
        </actor>
        <actor id="id149300" prototype="id580528">
          <attributes>
            <point id="position">
              <real id="x">125.5</real>
              <real id="y">229.5</real>
            </point>
            <size id="size">
              <real id="width">52</real>
              <real id="height">183</real>
            </size>
            <angle id="rotation">0</angle>
          </attributes>
          <behaviors>
            <behavior id="id384043" class="MoveBehavior" enabled="true">
              <attributes>
                <text id="name">Move</text>
                <text id="bundleName">Move.behavior</text>
                <angle id="direction">180</angle>
                <index id="space">0</index>
                <index id="moveType">0</index>
                <real id="speed">25</real>
              </attributes>
            </behavior>
          </behaviors>
          <aspects>
            <graphics>
              <attributes>
                <integer id="tileWidth" name="tileWidth">0</integer>
                <integer id="tileHeight" name="tileHeight">0</integer>
              </attributes>
            </graphics>
            <motion />
            <physics>
              <attributes />
            </physics>
          </aspects>
        </actor>
      </actors>
      <attributes>
        <text id="name">Background</text>
        <boolean id="scrollable">true</boolean>
      </attributes>
    </layer>
  </layers>
  <attributes>
    <text id="name">Play</text>
    <real id="time">0</real>
    <size id="size">
      <real id="width">480</real>
      <real id="height">320</real>
    </size>
    <boolean id="wrapX">false</boolean>
    <boolean id="wrapY">false</boolean>
    <point id="gravity">
      <real id="x">0</real>
      <real id="y">0</real>
    </point>
    <color id="color">
      <real id="red">0</real>
      <real id="green">0</real>
      <real id="blue">0</real>
      <real id="alpha">1</real>
    </color>
    <rect id="camera">
      <point id="origin">
        <real id="x">0</real>
        <real id="y">0</real>
      </point>
      <size id="size">
        <real id="width">480</real>
        <real id="height">320</real>
      </size>
      <size id="trackingArea">
        <real id="width">400</real>
        <real id="height">260</real>
      </size>
      <real id="rotation">0</real>
    </rect>
    <attributes id="autorotate">
      <boolean id="landscapeLeft">true</boolean>
      <boolean id="portrait">false</boolean>
      <boolean id="landscapeRight">false</boolean>
      <boolean id="portraitUpsideDown">false</boolean>
    </attributes>
  </attributes>
</scene>